no_nickname_mcp_test/__init__.py
no_nickname_mcp_test-0.1.0.dist-info/METADATA
no_nickname_mcp_test-0.1.0.dist-info/WHEEL
no_nickname_mcp_test-0.1.0.dist-info/entry_points.txt
no_nickname_mcp_test-0.1.0.dist-info/RECORD
