Metadata-Version: 2.4
Name: no-nickname-mcp-test
Version: 0.1.0
Summary: Add your description here
Author-email: qianchao <980569038@qq.com>
Requires-Python: >=3.13
Requires-Dist: mcp[cli]>=1.9.3
